LICENSE.txt
MANIFEST.in
README.md
VERSION
setup.cfg
setup.py
pynuwa/__init__.py
pynuwa.egg-info/PKG-INFO
pynuwa.egg-info/SOURCES.txt
pynuwa.egg-info/dependency_links.txt
pynuwa.egg-info/top_level.txt