Metadata-Version: 2.1
Name: pynuwa
Version: 0.0.1
Summary: pynuwa
Home-page: https://gitee.com/chaos-god/pynuwa.git
Author: pynuwa
Author-email: 9239867+chaos-god@user.noreply.gitee.com
License: UNKNOWN
Platform: UNKNOWN
License-File: LICENSE.txt
